{
  "updatedAt": "2026-05-01T04:28:27.888Z",
  "tools": {
    "atlassian-user-info": {
      "type": "object",
      "properties": {},
      "$schema": "http://json-schema.org/draft-07/schema#"
    },
    "get-accessible-atlassian-resources": {
      "type": "object",
      "properties": {},
      "$schema": "http://json-schema.org/draft-07/schema#"
    },
    "get-confluence-page": {
      "type": "object",
      "properties": {
        "cloudId": {
          "type": "string",
          "description": "Cloud ID (UUID or site URL)"
        },
        "pageId": {
          "type": "string",
          "description": "Page or blog post ID, or a Confluence tiny link ID (the encoded part from /wiki/x/ URLs, e.g., Fc1bBw)"
        },
        "contentType": {
          "type": "string",
          "enum": [
            "page",
            "blog"
          ],
          "default": "page",
          "description": "Type of content: page or blog post"
        },
        "contentFormat": {
          "type": "string",
          "enum": [
            "markdown",
            "adf"
          ],
          "description": "Content format for page body. Use \"html\" to write or read Confluence content as structured HTML — supports headings, paragraphs, tables, task lists, panels (info/warning/note/success/error), two/three-column layouts, code blocks, and inline formatting. HTML is round-trip safe and preserves inline comments. Use \"markdown\" for simplified plain text. Use \"adf\" (Atlassian Document Format, JSON) for full programmatic fidelity. Defaults to ADF when omitted."
        }
      },
      "required": [
        "cloudId",
        "pageId"
      ],
      "additionalProperties": false,
      "$schema": "http://json-schema.org/draft-07/schema#"
    },
    "search-confluence-using-cql": {
      "type": "object",
      "properties": {
        "cloudId": {
          "type": "string",
          "description": "Cloud ID (UUID or site URL)"
        },
        "cql": {
          "type": "string",
          "description": "CQL query string (e.g., \"title ~ \"meeting\" AND type = page\")"
        },
        "cqlcontext": {
          "type": "string",
          "description": "CQL context"
        },
        "cursor": {
          "type": "string",
          "description": "Pagination cursor"
        },
        "expand": {
          "type": "string",
          "description": "Properties to expand"
        },
        "limit": {
          "type": "number",
          "description": "Max results (default: 25, max: 250)"
        },
        "prev": {
          "type": "boolean",
          "description": "Include previous page link"
        },
        "next": {
          "type": "boolean",
          "description": "Include next page link"
        }
      },
      "required": [
        "cloudId",
        "cql"
      ],
      "additionalProperties": false,
      "$schema": "http://json-schema.org/draft-07/schema#"
    },
    "get-confluence-spaces": {
      "type": "object",
      "properties": {
        "cloudId": {
          "type": "string",
          "description": "Cloud ID (UUID or site URL)"
        },
        "ids": {
          "anyOf": [
            {
              "type": "string"
            },
            {
              "type": "array",
              "items": {
                "type": "number"
              }
            }
          ],
          "description": "Space IDs"
        },
        "keys": {
          "anyOf": [
            {
              "type": "string"
            },
            {
              "type": "array",
              "items": {
                "type": "string"
              }
            }
          ],
          "description": "Space keys"
        },
        "type": {
          "type": "string",
          "enum": [
            "global",
            "personal"
          ],
          "description": "Space type"
        },
        "status": {
          "type": "string",
          "enum": [
            "current",
            "archived"
          ],
          "description": "Space status"
        },
        "labels": {
          "anyOf": [
            {
              "type": "string"
            },
            {
              "type": "array",
              "items": {
                "type": "string"
              }
            }
          ],
          "description": "Space labels"
        },
        "favourite": {
          "type": "boolean",
          "description": "Favorite spaces only"
        },
        "favoritedBy": {
          "type": "string",
          "description": "User favorites"
        },
        "expand": {
          "anyOf": [
            {
              "type": "string"
            },
            {
              "type": "array",
              "items": {
                "type": "string"
              }
            }
          ],
          "description": "Properties to expand"
        },
        "start": {
          "type": "number",
          "description": "Start index"
        },
        "limit": {
          "type": "number",
          "description": "Max results (default: 25, max: 250)"
        }
      },
      "required": [
        "cloudId"
      ],
      "additionalProperties": false,
      "$schema": "http://json-schema.org/draft-07/schema#"
    },
    "get-pages-in-confluence-space": {
      "type": "object",
      "properties": {
        "cloudId": {
          "type": "string",
          "description": "Cloud ID (UUID or site URL)"
        },
        "spaceId": {
          "type": "string",
          "description": "Space ID"
        },
        "contentType": {
          "type": "string",
          "enum": [
            "page",
            "blog"
          ],
          "default": "page",
          "description": "Type of content: page or blog post"
        },
        "limit": {
          "type": "number",
          "description": "Max results (default: 25, max: 250)"
        },
        "cursor": {
          "type": "string",
          "description": "Pagination cursor"
        },
        "status": {
          "type": "string",
          "enum": [
            "current",
            "archived",
            "deleted",
            "trashed"
          ],
          "description": "Page status"
        },
        "title": {
          "type": "string",
          "description": "Title filter"
        },
        "sort": {
          "type": "string",
          "enum": [
            "id",
            "-id",
            "created-date",
            "-created-date",
            "modified-date",
            "-modified-date",
            "title",
            "-title"
          ],
          "description": "Sort order"
        },
        "contentFormat": {
          "type": "string",
          "enum": [
            "markdown",
            "adf"
          ],
          "description": "Content format for page body. Use \"html\" to write or read Confluence content as structured HTML — supports headings, paragraphs, tables, task lists, panels (info/warning/note/success/error), two/three-column layouts, code blocks, and inline formatting. HTML is round-trip safe and preserves inline comments. Use \"markdown\" for simplified plain text. Use \"adf\" (Atlassian Document Format, JSON) for full programmatic fidelity. Defaults to ADF when omitted."
        }
      },
      "required": [
        "cloudId",
        "spaceId"
      ],
      "additionalProperties": false,
      "$schema": "http://json-schema.org/draft-07/schema#"
    },
    "get-confluence-page-footer-comments": {
      "type": "object",
      "properties": {
        "cloudId": {
          "type": "string",
          "description": "Cloud ID (UUID or site URL)"
        },
        "pageId": {
          "type": "string",
          "description": "Page or blog post ID, or a Confluence tiny link ID (the encoded part from /wiki/x/ URLs, e.g., Fc1bBw)"
        },
        "contentType": {
          "type": "string",
          "enum": [
            "page",
            "blog"
          ],
          "default": "page",
          "description": "Type of content: page or blog post"
        },
        "limit": {
          "type": "number",
          "description": "Max comments"
        },
        "cursor": {
          "type": "string",
          "description": "Pagination cursor"
        },
        "status": {
          "type": "string",
          "enum": [
            "current",
            "archived",
            "trashed",
            "deleted",
            "historical",
            "draft"
          ],
          "default": "current",
          "description": "Comment status"
        },
        "sort": {
          "type": "string",
          "enum": [
            "id",
            "-id",
            "created-date",
            "-created-date"
          ],
          "description": "Sort order"
        },
        "contentFormat": {
          "type": "string",
          "enum": [
            "markdown",
            "adf"
          ],
          "description": "Content format for page body. Use \"html\" to write or read Confluence content as structured HTML — supports headings, paragraphs, tables, task lists, panels (info/warning/note/success/error), two/three-column layouts, code blocks, and inline formatting. HTML is round-trip safe and preserves inline comments. Use \"markdown\" for simplified plain text. Use \"adf\" (Atlassian Document Format, JSON) for full programmatic fidelity. Defaults to ADF when omitted."
        }
      },
      "required": [
        "cloudId",
        "pageId"
      ],
      "additionalProperties": false,
      "$schema": "http://json-schema.org/draft-07/schema#"
    },
    "get-confluence-page-inline-comments": {
      "type": "object",
      "properties": {
        "cloudId": {
          "type": "string",
          "description": "Cloud ID (UUID or site URL)"
        },
        "pageId": {
          "type": "string",
          "description": "Page or blog post ID, or a Confluence tiny link ID (the encoded part from /wiki/x/ URLs, e.g., Fc1bBw)"
        },
        "contentType": {
          "type": "string",
          "enum": [
            "page",
            "blog"
          ],
          "default": "page",
          "description": "Type of content: page or blog post"
        },
        "limit": {
          "type": "number",
          "description": "Max comments"
        },
        "cursor": {
          "type": "string",
          "description": "Pagination cursor"
        },
        "status": {
          "type": "string",
          "enum": [
            "current",
            "archived",
            "trashed",
            "deleted",
            "historical",
            "draft"
          ],
          "default": "current",
          "description": "Comment status"
        },
        "resolutionStatus": {
          "type": "string",
          "enum": [
            "resolved",
            "open",
            "dangling",
            "reopened"
          ],
          "default": "open",
          "description": "Resolution status"
        },
        "sort": {
          "type": "string",
          "enum": [
            "id",
            "-id",
            "created-date",
            "-created-date"
          ],
          "description": "Sort order"
        },
        "contentFormat": {
          "type": "string",
          "enum": [
            "markdown",
            "adf"
          ],
          "description": "Content format for page body. Use \"html\" to write or read Confluence content as structured HTML — supports headings, paragraphs, tables, task lists, panels (info/warning/note/success/error), two/three-column layouts, code blocks, and inline formatting. HTML is round-trip safe and preserves inline comments. Use \"markdown\" for simplified plain text. Use \"adf\" (Atlassian Document Format, JSON) for full programmatic fidelity. Defaults to ADF when omitted."
        }
      },
      "required": [
        "cloudId",
        "pageId"
      ],
      "additionalProperties": false,
      "$schema": "http://json-schema.org/draft-07/schema#"
    },
    "get-confluence-comment-children": {
      "type": "object",
      "properties": {
        "cloudId": {
          "type": "string",
          "description": "Cloud ID (UUID or site URL)"
        },
        "commentId": {
          "type": "string",
          "description": "Parent comment ID"
        },
        "commentType": {
          "type": "string",
          "enum": [
            "footer",
            "inline"
          ],
          "description": "Comment type"
        },
        "limit": {
          "type": "number",
          "description": "Max replies"
        },
        "cursor": {
          "type": "string",
          "description": "Pagination cursor"
        },
        "sort": {
          "type": "string",
          "enum": [
            "id",
            "-id",
            "created-date",
            "-created-date"
          ],
          "description": "Sort order"
        },
        "contentFormat": {
          "type": "string",
          "enum": [
            "markdown",
            "adf"
          ],
          "description": "Content format for page body. Use \"html\" to write or read Confluence content as structured HTML — supports headings, paragraphs, tables, task lists, panels (info/warning/note/success/error), two/three-column layouts, code blocks, and inline formatting. HTML is round-trip safe and preserves inline comments. Use \"markdown\" for simplified plain text. Use \"adf\" (Atlassian Document Format, JSON) for full programmatic fidelity. Defaults to ADF when omitted."
        }
      },
      "required": [
        "cloudId",
        "commentId",
        "commentType"
      ],
      "additionalProperties": false,
      "$schema": "http://json-schema.org/draft-07/schema#"
    },
    "get-confluence-page-descendants": {
      "type": "object",
      "properties": {
        "cloudId": {
          "type": "string",
          "description": "Cloud ID (UUID or site URL)"
        },
        "pageId": {
          "type": "string",
          "description": "Page or blog post ID, or a Confluence tiny link ID (the encoded part from /wiki/x/ URLs, e.g., Fc1bBw)"
        },
        "limit": {
          "type": "number",
          "description": "Max descendants"
        },
        "depth": {
          "type": "number",
          "description": "Max depth"
        },
        "cursor": {
          "type": "string",
          "description": "Pagination cursor"
        }
      },
      "required": [
        "cloudId",
        "pageId"
      ],
      "additionalProperties": false,
      "$schema": "http://json-schema.org/draft-07/schema#"
    },
    "create-confluence-page": {
      "type": "object",
      "properties": {
        "cloudId": {
          "type": "string",
          "description": "Cloud ID (UUID or site URL)"
        },
        "spaceId": {
          "type": "string",
          "description": "Space ID"
        },
        "contentType": {
          "type": "string",
          "enum": [
            "page",
            "blog"
          ],
          "default": "page",
          "description": "Type of content: page or blog post"
        },
        "title": {
          "type": "string",
          "description": "Page or blog post title"
        },
        "status": {
          "type": "string",
          "enum": [
            "current",
            "draft"
          ],
          "default": "current",
          "description": "Status (draft for unpublished)"
        },
        "parentId": {
          "type": "string",
          "description": "Parent page ID (pages only, ignored for blogs)"
        },
        "body": {
          "type": "string",
          "description": "Page/comment body. When contentFormat is \"html\", use standard HTML for headings (<h1>-<h6>), paragraphs (<p>), bold (<strong>), italic (<em>), tables (<table>/<thead>/<tbody>/<tr>/<th>/<td>), links (<a href=\"URL\">), code (<pre><code class=\"language-python\">), and lists (<ul>/<ol>/<li>). For Confluence-specific elements use data-type attributes (not CSS classes): Panels: <div data-type=\"panel-info|warning|note|success|error\"><p>text</p></div>. Status lozenge: <span data-type=\"status\" data-color=\"green|red|yellow|blue|neutral|purple\">Label</span>. Task list: <ul data-type=\"task-list\"><li data-type=\"task-item\"><input type=\"checkbox\"> Item</li></ul>. Decision list: <ul data-type=\"decision-list\"><li data-type=\"decision-item\" data-state=\"DECIDED|UNDECIDED\">text</li></ul>. Expand/collapse: <details><summary>Title</summary><p>content</p></details>. User mention: <span data-type=\"mention\" data-user-id=\"ACCOUNT_ID\">@Name</span>. Two-column layout: <section data-type=\"layout-two-equal\"><div data-type=\"column\"><p>Left</p></div><div data-type=\"column\"><p>Right</p></div></section>. Smart link (inline preview): <a href=\"URL\" data-card-appearance=\"inline\">text</a>. Date: <time datetime=\"YYYY-MM-DD\">label</time>. Never wrap content in <html>, <head>, or <body> tags."
        },
        "contentFormat": {
          "type": "string",
          "enum": [
            "markdown",
            "adf"
          ],
          "description": "Content format for page body. Use \"html\" to write or read Confluence content as structured HTML — supports headings, paragraphs, tables, task lists, panels (info/warning/note/success/error), two/three-column layouts, code blocks, and inline formatting. HTML is round-trip safe and preserves inline comments. Use \"markdown\" for simplified plain text. Use \"adf\" (Atlassian Document Format, JSON) for full programmatic fidelity. Defaults to ADF when omitted."
        },
        "isPrivate": {
          "type": "boolean",
          "description": "Make private"
        },
        "subtype": {
          "type": "string",
          "enum": [
            "live"
          ],
          "description": "Page subtype (pages only, ignored for blogs)"
        }
      },
      "required": [
        "cloudId",
        "spaceId",
        "body"
      ],
      "additionalProperties": false,
      "$schema": "http://json-schema.org/draft-07/schema#"
    },
    "update-confluence-page": {
      "type": "object",
      "properties": {
        "cloudId": {
          "type": "string",
          "description": "Cloud ID (UUID or site URL)"
        },
        "pageId": {
          "type": "string",
          "description": "Page or blog post ID, or a Confluence tiny link ID (the encoded part from /wiki/x/ URLs, e.g., Fc1bBw)"
        },
        "contentType": {
          "type": "string",
          "enum": [
            "page",
            "blog"
          ],
          "default": "page",
          "description": "Type of content: page or blog post"
        },
        "title": {
          "type": "string",
          "description": "New title"
        },
        "status": {
          "type": "string",
          "enum": [
            "current",
            "draft"
          ],
          "default": "current",
          "description": "Page status"
        },
        "spaceId": {
          "type": "string",
          "description": "Space ID"
        },
        "parentId": {
          "type": "string",
          "description": "Parent page ID (pages only, ignored for blogs)"
        },
        "body": {
          "type": "string",
          "description": "Page/comment body. When contentFormat is \"html\", use standard HTML for headings (<h1>-<h6>), paragraphs (<p>), bold (<strong>), italic (<em>), tables (<table>/<thead>/<tbody>/<tr>/<th>/<td>), links (<a href=\"URL\">), code (<pre><code class=\"language-python\">), and lists (<ul>/<ol>/<li>). For Confluence-specific elements use data-type attributes (not CSS classes): Panels: <div data-type=\"panel-info|warning|note|success|error\"><p>text</p></div>. Status lozenge: <span data-type=\"status\" data-color=\"green|red|yellow|blue|neutral|purple\">Label</span>. Task list: <ul data-type=\"task-list\"><li data-type=\"task-item\"><input type=\"checkbox\"> Item</li></ul>. Decision list: <ul data-type=\"decision-list\"><li data-type=\"decision-item\" data-state=\"DECIDED|UNDECIDED\">text</li></ul>. Expand/collapse: <details><summary>Title</summary><p>content</p></details>. User mention: <span data-type=\"mention\" data-user-id=\"ACCOUNT_ID\">@Name</span>. Two-column layout: <section data-type=\"layout-two-equal\"><div data-type=\"column\"><p>Left</p></div><div data-type=\"column\"><p>Right</p></div></section>. Smart link (inline preview): <a href=\"URL\" data-card-appearance=\"inline\">text</a>. Date: <time datetime=\"YYYY-MM-DD\">label</time>. Never wrap content in <html>, <head>, or <body> tags."
        },
        "contentFormat": {
          "type": "string",
          "enum": [
            "markdown",
            "adf"
          ],
          "description": "Content format for page body. Use \"html\" to write or read Confluence content as structured HTML — supports headings, paragraphs, tables, task lists, panels (info/warning/note/success/error), two/three-column layouts, code blocks, and inline formatting. HTML is round-trip safe and preserves inline comments. Use \"markdown\" for simplified plain text. Use \"adf\" (Atlassian Document Format, JSON) for full programmatic fidelity. Defaults to ADF when omitted."
        },
        "versionMessage": {
          "type": "string",
          "description": "Version message"
        },
        "includeBody": {
          "type": "boolean",
          "default": false,
          "description": "If true, include the page body in the response; if false, omit it to reduce payload size."
        }
      },
      "required": [
        "cloudId",
        "pageId",
        "body"
      ],
      "additionalProperties": false,
      "$schema": "http://json-schema.org/draft-07/schema#"
    },
    "create-confluence-footer-comment": {
      "type": "object",
      "properties": {
        "cloudId": {
          "type": "string",
          "description": "Cloud ID (UUID or site URL)"
        },
        "pageId": {
          "type": "string",
          "description": "Page or blog post ID, or a Confluence tiny link ID (the encoded part from /wiki/x/ URLs, e.g., Fc1bBw)"
        },
        "contentType": {
          "type": "string",
          "enum": [
            "page",
            "blog"
          ],
          "default": "page",
          "description": "Type of content: page or blog post"
        },
        "parentCommentId": {
          "type": "string",
          "description": "Parent comment ID for replies"
        },
        "attachmentId": {
          "type": "string",
          "description": "Attachment ID to include"
        },
        "customContentId": {
          "type": "string",
          "description": "Custom content ID to include"
        },
        "body": {
          "type": "string",
          "description": "Page/comment body. When contentFormat is \"html\", use standard HTML for headings (<h1>-<h6>), paragraphs (<p>), bold (<strong>), italic (<em>), tables (<table>/<thead>/<tbody>/<tr>/<th>/<td>), links (<a href=\"URL\">), code (<pre><code class=\"language-python\">), and lists (<ul>/<ol>/<li>). For Confluence-specific elements use data-type attributes (not CSS classes): Panels: <div data-type=\"panel-info|warning|note|success|error\"><p>text</p></div>. Status lozenge: <span data-type=\"status\" data-color=\"green|red|yellow|blue|neutral|purple\">Label</span>. Task list: <ul data-type=\"task-list\"><li data-type=\"task-item\"><input type=\"checkbox\"> Item</li></ul>. Decision list: <ul data-type=\"decision-list\"><li data-type=\"decision-item\" data-state=\"DECIDED|UNDECIDED\">text</li></ul>. Expand/collapse: <details><summary>Title</summary><p>content</p></details>. User mention: <span data-type=\"mention\" data-user-id=\"ACCOUNT_ID\">@Name</span>. Two-column layout: <section data-type=\"layout-two-equal\"><div data-type=\"column\"><p>Left</p></div><div data-type=\"column\"><p>Right</p></div></section>. Smart link (inline preview): <a href=\"URL\" data-card-appearance=\"inline\">text</a>. Date: <time datetime=\"YYYY-MM-DD\">label</time>. Never wrap content in <html>, <head>, or <body> tags."
        },
        "contentFormat": {
          "type": "string",
          "enum": [
            "markdown",
            "adf"
          ],
          "description": "Content format for page body. Use \"html\" to write or read Confluence content as structured HTML — supports headings, paragraphs, tables, task lists, panels (info/warning/note/success/error), two/three-column layouts, code blocks, and inline formatting. HTML is round-trip safe and preserves inline comments. Use \"markdown\" for simplified plain text. Use \"adf\" (Atlassian Document Format, JSON) for full programmatic fidelity. Defaults to ADF when omitted."
        }
      },
      "required": [
        "cloudId",
        "body"
      ],
      "additionalProperties": false,
      "$schema": "http://json-schema.org/draft-07/schema#"
    },
    "create-confluence-inline-comment": {
      "type": "object",
      "properties": {
        "cloudId": {
          "type": "string",
          "description": "Cloud ID (UUID or site URL)"
        },
        "pageId": {
          "type": "string",
          "description": "Page or blog post ID, or a Confluence tiny link ID (the encoded part from /wiki/x/ URLs, e.g., Fc1bBw)"
        },
        "contentType": {
          "type": "string",
          "enum": [
            "page",
            "blog"
          ],
          "default": "page",
          "description": "Type of content: page or blog post"
        },
        "parentCommentId": {
          "type": "string",
          "description": "Parent comment ID for replies"
        },
        "body": {
          "type": "string",
          "description": "Page/comment body. When contentFormat is \"html\", use standard HTML for headings (<h1>-<h6>), paragraphs (<p>), bold (<strong>), italic (<em>), tables (<table>/<thead>/<tbody>/<tr>/<th>/<td>), links (<a href=\"URL\">), code (<pre><code class=\"language-python\">), and lists (<ul>/<ol>/<li>). For Confluence-specific elements use data-type attributes (not CSS classes): Panels: <div data-type=\"panel-info|warning|note|success|error\"><p>text</p></div>. Status lozenge: <span data-type=\"status\" data-color=\"green|red|yellow|blue|neutral|purple\">Label</span>. Task list: <ul data-type=\"task-list\"><li data-type=\"task-item\"><input type=\"checkbox\"> Item</li></ul>. Decision list: <ul data-type=\"decision-list\"><li data-type=\"decision-item\" data-state=\"DECIDED|UNDECIDED\">text</li></ul>. Expand/collapse: <details><summary>Title</summary><p>content</p></details>. User mention: <span data-type=\"mention\" data-user-id=\"ACCOUNT_ID\">@Name</span>. Two-column layout: <section data-type=\"layout-two-equal\"><div data-type=\"column\"><p>Left</p></div><div data-type=\"column\"><p>Right</p></div></section>. Smart link (inline preview): <a href=\"URL\" data-card-appearance=\"inline\">text</a>. Date: <time datetime=\"YYYY-MM-DD\">label</time>. Never wrap content in <html>, <head>, or <body> tags."
        },
        "contentFormat": {
          "type": "string",
          "enum": [
            "markdown",
            "adf"
          ],
          "description": "Content format for page body. Use \"html\" to write or read Confluence content as structured HTML — supports headings, paragraphs, tables, task lists, panels (info/warning/note/success/error), two/three-column layouts, code blocks, and inline formatting. HTML is round-trip safe and preserves inline comments. Use \"markdown\" for simplified plain text. Use \"adf\" (Atlassian Document Format, JSON) for full programmatic fidelity. Defaults to ADF when omitted."
        },
        "inlineCommentProperties": {
          "type": "object",
          "properties": {
            "textSelection": {
              "type": "string",
              "description": "Text to highlight"
            },
            "textSelectionMatchCount": {
              "type": "number",
              "description": "Total matches on page"
            },
            "textSelectionMatchIndex": {
              "type": "number",
              "description": "Which match to highlight (0-based)"
            }
          },
          "required": [
            "textSelection",
            "textSelectionMatchCount",
            "textSelectionMatchIndex"
          ],
          "additionalProperties": false,
          "description": "Text selection properties for highlighting"
        }
      },
      "required": [
        "cloudId",
        "body"
      ],
      "additionalProperties": false,
      "$schema": "http://json-schema.org/draft-07/schema#"
    },
    "get-jira-issue": {
      "type": "object",
      "properties": {
        "cloudId": {
          "type": "string",
          "description": "Cloud ID (UUID or site URL)"
        },
        "issueIdOrKey": {
          "type": "string",
          "description": "Issue ID or key (e.g., PROJ-123 or 10000)"
        },
        "fields": {
          "type": "array",
          "items": {
            "type": "string"
          }
        },
        "fieldsByKeys": {
          "type": "boolean"
        },
        "expand": {
          "type": "string"
        },
        "properties": {
          "type": "array",
          "items": {
            "type": "string"
          }
        },
        "updateHistory": {
          "type": "boolean"
        },
        "failFast": {
          "type": "boolean"
        },
        "responseContentFormat": {
          "type": "string",
          "enum": [
            "markdown",
            "adf"
          ],
          "description": "Content format for page body. Use \"html\" to write or read Confluence content as structured HTML — supports headings, paragraphs, tables, task lists, panels (info/warning/note/success/error), two/three-column layouts, code blocks, and inline formatting. HTML is round-trip safe and preserves inline comments. Use \"markdown\" for simplified plain text. Use \"adf\" (Atlassian Document Format, JSON) for full programmatic fidelity. Defaults to ADF when omitted."
        }
      },
      "required": [
        "cloudId",
        "issueIdOrKey"
      ],
      "additionalProperties": false,
      "$schema": "http://json-schema.org/draft-07/schema#"
    },
    "edit-jira-issue": {
      "type": "object",
      "properties": {
        "cloudId": {
          "type": "string",
          "description": "Cloud ID (UUID or site URL)"
        },
        "issueIdOrKey": {
          "type": "string",
          "description": "Issue ID or key (e.g., PROJ-123 or 10000)"
        },
        "fields": {
          "type": "object",
          "additionalProperties": {}
        },
        "contentFormat": {
          "type": "string",
          "enum": [
            "markdown",
            "adf"
          ],
          "description": "Content format for page body. Use \"html\" to write or read Confluence content as structured HTML — supports headings, paragraphs, tables, task lists, panels (info/warning/note/success/error), two/three-column layouts, code blocks, and inline formatting. HTML is round-trip safe and preserves inline comments. Use \"markdown\" for simplified plain text. Use \"adf\" (Atlassian Document Format, JSON) for full programmatic fidelity. Defaults to ADF when omitted."
        },
        "responseContentFormat": {
          "type": "string",
          "enum": [
            "markdown",
            "adf"
          ],
          "description": "Content format for page body. Use \"html\" to write or read Confluence content as structured HTML — supports headings, paragraphs, tables, task lists, panels (info/warning/note/success/error), two/three-column layouts, code blocks, and inline formatting. HTML is round-trip safe and preserves inline comments. Use \"markdown\" for simplified plain text. Use \"adf\" (Atlassian Document Format, JSON) for full programmatic fidelity. Defaults to ADF when omitted."
        }
      },
      "required": [
        "cloudId",
        "issueIdOrKey",
        "fields"
      ],
      "additionalProperties": false,
      "$schema": "http://json-schema.org/draft-07/schema#"
    },
    "create-jira-issue": {
      "type": "object",
      "properties": {
        "cloudId": {
          "type": "string",
          "description": "Cloud ID (UUID or site URL)"
        },
        "projectKey": {
          "type": "string",
          "description": "Project key"
        },
        "issueTypeName": {
          "type": "string",
          "description": "Type (Task, Bug, Story)"
        },
        "summary": {
          "type": "string"
        },
        "description": {
          "type": "string",
          "description": "Issue description"
        },
        "parent": {
          "type": "string",
          "description": "Parent for subtasks"
        },
        "assignee_account_id": {
          "type": "string",
          "description": "Assignee ID"
        },
        "additional_fields": {
          "type": "object",
          "additionalProperties": {},
          "description": "REQUIRED for custom fields. This is the ONLY parameter to set priority, labels, custom fields, or any other Jira fields not listed above. Pass a JSON object with field names as keys. Example: {\"priority\": {\"name\": \"High\"}, \"labels\": [\"bug\"], \"customfield_10001\": \"value\"}."
        },
        "transition": {
          "type": "object",
          "properties": {
            "id": {
              "type": "string",
              "description": "The workflow transition ID to apply during issue creation"
            }
          },
          "required": [
            "id"
          ],
          "additionalProperties": false,
          "description": "Optional workflow transition to apply during creation. Use getTransitionsForJiraIssue to find valid transition IDs. Placed at top level of Jira API request, not inside fields."
        },
        "contentFormat": {
          "type": "string",
          "enum": [
            "markdown",
            "adf"
          ],
          "description": "Content format for page body. Use \"html\" to write or read Confluence content as structured HTML — supports headings, paragraphs, tables, task lists, panels (info/warning/note/success/error), two/three-column layouts, code blocks, and inline formatting. HTML is round-trip safe and preserves inline comments. Use \"markdown\" for simplified plain text. Use \"adf\" (Atlassian Document Format, JSON) for full programmatic fidelity. Defaults to ADF when omitted."
        },
        "responseContentFormat": {
          "type": "string",
          "enum": [
            "markdown",
            "adf"
          ],
          "description": "Content format for page body. Use \"html\" to write or read Confluence content as structured HTML — supports headings, paragraphs, tables, task lists, panels (info/warning/note/success/error), two/three-column layouts, code blocks, and inline formatting. HTML is round-trip safe and preserves inline comments. Use \"markdown\" for simplified plain text. Use \"adf\" (Atlassian Document Format, JSON) for full programmatic fidelity. Defaults to ADF when omitted."
        }
      },
      "required": [
        "cloudId",
        "projectKey",
        "issueTypeName",
        "summary"
      ],
      "additionalProperties": false,
      "$schema": "http://json-schema.org/draft-07/schema#"
    },
    "get-transitions-for-jira-issue": {
      "type": "object",
      "properties": {
        "cloudId": {
          "type": "string",
          "description": "Cloud ID (UUID or site URL)"
        },
        "issueIdOrKey": {
          "type": "string",
          "description": "Issue ID or key (e.g., PROJ-123 or 10000)"
        },
        "expand": {
          "type": "string"
        },
        "transitionId": {
          "type": "string"
        },
        "skipRemoteOnlyCondition": {
          "type": "boolean"
        },
        "includeUnavailableTransitions": {
          "type": "boolean"
        },
        "sortByOpsBarAndStatus": {
          "type": "boolean"
        }
      },
      "required": [
        "cloudId",
        "issueIdOrKey"
      ],
      "additionalProperties": false,
      "$schema": "http://json-schema.org/draft-07/schema#"
    },
    "get-jira-issue-remote-issue-links": {
      "type": "object",
      "properties": {
        "cloudId": {
          "type": "string",
          "description": "Cloud ID (UUID or site URL)"
        },
        "issueIdOrKey": {
          "type": "string",
          "description": "Issue ID or key (e.g., PROJ-123 or 10000)"
        },
        "globalId": {
          "type": "string"
        }
      },
      "required": [
        "cloudId",
        "issueIdOrKey"
      ],
      "additionalProperties": false,
      "$schema": "http://json-schema.org/draft-07/schema#"
    },
    "get-visible-jira-projects": {
      "type": "object",
      "properties": {
        "cloudId": {
          "type": "string",
          "description": "Cloud ID (UUID or site URL)"
        },
        "searchString": {
          "type": "string"
        },
        "action": {
          "type": "string",
          "enum": [
            "view",
            "browse",
            "edit",
            "create"
          ],
          "default": "create"
        },
        "startAt": {
          "type": "number",
          "default": 0
        },
        "maxResults": {
          "type": "number",
          "maximum": 50,
          "default": 50
        },
        "expandIssueTypes": {
          "type": "boolean",
          "default": true
        }
      },
      "required": [
        "cloudId"
      ],
      "additionalProperties": false,
      "$schema": "http://json-schema.org/draft-07/schema#"
    },
    "get-jira-project-issue-types-metadata": {
      "type": "object",
      "properties": {
        "cloudId": {
          "type": "string",
          "description": "Cloud ID (UUID or site URL)"
        },
        "projectIdOrKey": {
          "type": "string"
        },
        "startAt": {
          "type": "number",
          "default": 0
        },
        "maxResults": {
          "type": "number",
          "maximum": 200,
          "default": 50
        }
      },
      "required": [
        "cloudId",
        "projectIdOrKey"
      ],
      "additionalProperties": false,
      "$schema": "http://json-schema.org/draft-07/schema#"
    },
    "get-jira-issue-type-meta-with-fields": {
      "type": "object",
      "properties": {
        "cloudId": {
          "type": "string",
          "description": "Cloud ID (UUID or site URL)"
        },
        "projectIdOrKey": {
          "type": "string"
        },
        "issueTypeId": {
          "type": "string"
        },
        "startAt": {
          "type": "number"
        },
        "maxResults": {
          "type": "number"
        }
      },
      "required": [
        "cloudId",
        "projectIdOrKey",
        "issueTypeId"
      ],
      "additionalProperties": false,
      "$schema": "http://json-schema.org/draft-07/schema#"
    },
    "add-comment-to-jira-issue": {
      "type": "object",
      "properties": {
        "cloudId": {
          "type": "string",
          "description": "Cloud ID (UUID or site URL)"
        },
        "issueIdOrKey": {
          "type": "string",
          "description": "Issue ID or key (e.g., PROJ-123 or 10000)"
        },
        "commentBody": {
          "type": "string",
          "description": "Comment body"
        },
        "commentVisibility": {
          "type": "object",
          "properties": {
            "type": {
              "type": "string",
              "enum": [
                "group",
                "role"
              ]
            },
            "value": {
              "type": "string"
            }
          },
          "required": [
            "type",
            "value"
          ],
          "additionalProperties": false
        },
        "contentFormat": {
          "type": "string",
          "enum": [
            "markdown",
            "adf"
          ],
          "description": "Content format for page body. Use \"html\" to write or read Confluence content as structured HTML — supports headings, paragraphs, tables, task lists, panels (info/warning/note/success/error), two/three-column layouts, code blocks, and inline formatting. HTML is round-trip safe and preserves inline comments. Use \"markdown\" for simplified plain text. Use \"adf\" (Atlassian Document Format, JSON) for full programmatic fidelity. Defaults to ADF when omitted."
        },
        "responseContentFormat": {
          "type": "string",
          "enum": [
            "markdown",
            "adf"
          ],
          "description": "Content format for page body. Use \"html\" to write or read Confluence content as structured HTML — supports headings, paragraphs, tables, task lists, panels (info/warning/note/success/error), two/three-column layouts, code blocks, and inline formatting. HTML is round-trip safe and preserves inline comments. Use \"markdown\" for simplified plain text. Use \"adf\" (Atlassian Document Format, JSON) for full programmatic fidelity. Defaults to ADF when omitted."
        }
      },
      "required": [
        "cloudId",
        "issueIdOrKey",
        "commentBody"
      ],
      "additionalProperties": false,
      "$schema": "http://json-schema.org/draft-07/schema#"
    },
    "transition-jira-issue": {
      "type": "object",
      "properties": {
        "cloudId": {
          "type": "string",
          "description": "Cloud ID (UUID or site URL)"
        },
        "issueIdOrKey": {
          "type": "string",
          "description": "Issue ID or key (e.g., PROJ-123 or 10000)"
        },
        "transition": {
          "type": "object",
          "properties": {
            "id": {
              "type": "string"
            }
          },
          "required": [
            "id"
          ],
          "additionalProperties": false
        },
        "fields": {
          "type": "object",
          "additionalProperties": {}
        },
        "update": {
          "type": "object",
          "additionalProperties": {
            "type": "array",
            "items": {
              "type": "object",
              "additionalProperties": {}
            }
          }
        },
        "historyMetadata": {
          "type": "object",
          "properties": {
            "type": {
              "type": "string"
            },
            "description": {
              "type": "string"
            },
            "descriptionKey": {
              "type": "string"
            },
            "activityDescription": {
              "type": "string"
            },
            "activityDescriptionKey": {
              "type": "string"
            },
            "emailDescription": {
              "type": "string"
            },
            "emailDescriptionKey": {
              "type": "string"
            },
            "actor": {
              "type": "object",
              "properties": {
                "id": {
                  "type": "string"
                },
                "displayName": {
                  "type": "string"
                },
                "type": {
                  "type": "string"
                },
                "avatarUrl": {
                  "type": "string"
                },
                "url": {
                  "type": "string"
                }
              },
              "additionalProperties": false
            },
            "generator": {
              "type": "object",
              "properties": {
                "id": {
                  "type": "string"
                },
                "displayName": {
                  "type": "string"
                },
                "type": {
                  "type": "string"
                },
                "avatarUrl": {
                  "type": "string"
                },
                "url": {
                  "type": "string"
                }
              },
              "additionalProperties": false
            },
            "cause": {
              "type": "object",
              "properties": {
                "id": {
                  "type": "string"
                },
                "displayName": {
                  "type": "string"
                },
                "type": {
                  "type": "string"
                },
                "avatarUrl": {
                  "type": "string"
                },
                "url": {
                  "type": "string"
                }
              },
              "additionalProperties": false
            },
            "extraData": {
              "type": "object",
              "additionalProperties": {
                "type": "string"
              }
            }
          },
          "additionalProperties": false
        }
      },
      "required": [
        "cloudId",
        "issueIdOrKey",
        "transition"
      ],
      "additionalProperties": false,
      "$schema": "http://json-schema.org/draft-07/schema#"
    },
    "search-jira-issues-using-jql": {
      "type": "object",
      "properties": {
        "cloudId": {
          "type": "string",
          "description": "Cloud ID (UUID or site URL)"
        },
        "jql": {
          "type": "string",
          "description": "JQL query"
        },
        "maxResults": {
          "type": "number",
          "maximum": 100,
          "default": 10,
          "description": "Max (50-100)"
        },
        "fields": {
          "type": "array",
          "items": {
            "type": "string"
          },
          "default": [
            "summary",
            "description",
            "status",
            "issuetype",
            "priority",
            "created"
          ]
        },
        "nextPageToken": {
          "type": "string",
          "description": "Page token"
        },
        "responseContentFormat": {
          "type": "string",
          "enum": [
            "markdown",
            "adf"
          ],
          "description": "Content format for page body. Use \"html\" to write or read Confluence content as structured HTML — supports headings, paragraphs, tables, task lists, panels (info/warning/note/success/error), two/three-column layouts, code blocks, and inline formatting. HTML is round-trip safe and preserves inline comments. Use \"markdown\" for simplified plain text. Use \"adf\" (Atlassian Document Format, JSON) for full programmatic fidelity. Defaults to ADF when omitted."
        }
      },
      "required": [
        "cloudId",
        "jql"
      ],
      "additionalProperties": false,
      "$schema": "http://json-schema.org/draft-07/schema#"
    },
    "lookup-jira-account-id": {
      "type": "object",
      "properties": {
        "cloudId": {
          "type": "string",
          "description": "Cloud ID (UUID or site URL)"
        },
        "searchString": {
          "type": "string"
        }
      },
      "required": [
        "cloudId",
        "searchString"
      ],
      "additionalProperties": false,
      "$schema": "http://json-schema.org/draft-07/schema#"
    },
    "add-worklog-to-jira-issue": {
      "type": "object",
      "properties": {
        "cloudId": {
          "type": "string",
          "description": "Cloud ID (UUID or site URL)"
        },
        "issueIdOrKey": {
          "type": "string",
          "description": "Issue ID or key (e.g., PROJ-123 or 10000)"
        },
        "timeSpent": {
          "type": "string",
          "description": "Time spent (e.g. 2h, 30m, 4d). Required for new worklogs; use to set or change time when updating."
        },
        "worklogId": {
          "type": "string",
          "description": "ID of an existing worklog to update. If omitted, a new worklog is created."
        },
        "commentBody": {
          "type": "string",
          "description": "Comment body"
        },
        "started": {
          "type": "string",
          "description": "When the work was started (ISO 8601 date-time, e.g. 2026-03-09T09:00:00.000+0000). If omitted, the worklog is booked at the current date/time."
        },
        "visibility": {
          "type": "object",
          "properties": {
            "type": {
              "type": "string",
              "enum": [
                "group",
                "role"
              ]
            },
            "value": {
              "type": "string"
            }
          },
          "required": [
            "type",
            "value"
          ],
          "additionalProperties": false
        },
        "contentFormat": {
          "type": "string",
          "enum": [
            "markdown",
            "adf"
          ],
          "description": "Content format for page body. Use \"html\" to write or read Confluence content as structured HTML — supports headings, paragraphs, tables, task lists, panels (info/warning/note/success/error), two/three-column layouts, code blocks, and inline formatting. HTML is round-trip safe and preserves inline comments. Use \"markdown\" for simplified plain text. Use \"adf\" (Atlassian Document Format, JSON) for full programmatic fidelity. Defaults to ADF when omitted."
        }
      },
      "required": [
        "cloudId",
        "issueIdOrKey",
        "timeSpent"
      ],
      "additionalProperties": false,
      "$schema": "http://json-schema.org/draft-07/schema#"
    },
    "get-issue-link-types": {
      "type": "object",
      "properties": {
        "cloudId": {
          "type": "string",
          "description": "Cloud ID (UUID or site URL)"
        }
      },
      "required": [
        "cloudId"
      ],
      "additionalProperties": false,
      "$schema": "http://json-schema.org/draft-07/schema#"
    },
    "create-issue-link": {
      "type": "object",
      "properties": {
        "cloudId": {
          "type": "string",
          "description": "Cloud ID (UUID or site URL)"
        },
        "inwardIssue": {
          "type": "string",
          "description": "Inward issue key (e.g. HSP-1)."
        },
        "outwardIssue": {
          "type": "string",
          "description": "Outward issue key (e.g. MKY-1)."
        },
        "type": {
          "type": "string",
          "description": "Link type name (e.g. Duplicate, Blocks, Clones, Relates). Use getIssueLinkTypes to list available types."
        },
        "comment": {
          "type": "string",
          "description": "Optional comment on the outward issue."
        },
        "contentFormat": {
          "type": "string",
          "enum": [
            "markdown",
            "adf"
          ],
          "description": "Content format for page body. Use \"html\" to write or read Confluence content as structured HTML — supports headings, paragraphs, tables, task lists, panels (info/warning/note/success/error), two/three-column layouts, code blocks, and inline formatting. HTML is round-trip safe and preserves inline comments. Use \"markdown\" for simplified plain text. Use \"adf\" (Atlassian Document Format, JSON) for full programmatic fidelity. Defaults to ADF when omitted."
        }
      },
      "required": [
        "cloudId",
        "inwardIssue",
        "outwardIssue",
        "type"
      ],
      "additionalProperties": false,
      "$schema": "http://json-schema.org/draft-07/schema#"
    },
    "search": {
      "type": "object",
      "properties": {
        "cloudId": {
          "type": "string",
          "description": "Not needed for this tool — cloudId is derived from your access token automatically"
        },
        "query": {
          "type": "string",
          "description": "The search query to use for Rovo Search"
        }
      },
      "required": [
        "query"
      ],
      "additionalProperties": false,
      "$schema": "http://json-schema.org/draft-07/schema#"
    },
    "fetch": {
      "type": "object",
      "properties": {
        "cloudId": {
          "type": "string",
          "description": "Not needed for this tool — cloudId is extracted from the ARI automatically"
        },
        "id": {
          "type": "string",
          "description": "Atlassian Resource Identifier (ARI) from search results, e.g., \"ari:cloud:jira:cloudId:issue/10107\" or \"ari:cloud:confluence:cloudId:page/123456789\""
        }
      },
      "required": [
        "id"
      ],
      "additionalProperties": false,
      "$schema": "http://json-schema.org/draft-07/schema#"
    }
  }
}